[
    {
        "praca": "SP Barretos",
        "preco_vista": 315.0,
        "preco_30d": "319.00",
        "variacao": "0.00",
        "data_coleta": "2026-01-24"
    },
    {
        "praca": "SP Araçatuba",
        "preco_vista": 315.0,
        "preco_30d": "319.00",
        "variacao": "0.00",
        "data_coleta": "2026-01-24"
    },
    {
        "praca": "MG Triângulo",
        "preco_vista": 301.5,
        "preco_30d": "305.00",
        "variacao": "-4.30",
        "data_coleta": "2026-01-24"
    },
    {
        "praca": "MG B.Horizonte",
        "preco_vista": 306.0,
        "preco_30d": "310.00",
        "variacao": "-2.71",
        "data_coleta": "2026-01-24"
    },
    {
        "praca": "MG Norte",
        "preco_vista": 301.5,
        "preco_30d": "305.00",
        "variacao": "-4.30",
        "data_coleta": "2026-01-24"
    },
    {
        "praca": "MG Sul",
        "preco_vista": 305.0,
        "preco_30d": "309.00",
        "variacao": "-3.03",
        "data_coleta": "2026-01-24"
    },
    {
        "praca": "GO Goiânia",
        "preco_vista": 303.5,
        "preco_30d": "307.00",
        "variacao": "-3.66",
        "data_coleta": "2026-01-24"
    },
    {
        "praca": "GO Reg. Sul",
        "preco_vista": 304.0,
        "preco_30d": "308.00",
        "variacao": "-3.34",
        "data_coleta": "2026-01-24"
    },
    {
        "praca": "MS Dourados",
        "preco_vista": 302.5,
        "preco_30d": "306.00",
        "variacao": "-3.98",
        "data_coleta": "2026-01-24"
    },
    {
        "praca": "MS C. Grande",
        "preco_vista": 302.5,
        "preco_30d": "306.00",
        "variacao": "-3.98",
        "data_coleta": "2026-01-24"
    },
    {
        "praca": "MS Três Lagoas",
        "preco_vista": 301.5,
        "preco_30d": "305.00",
        "variacao": "-4.30",
        "data_coleta": "2026-01-24"
    },
    {
        "praca": "RS Oeste (kg)",
        "preco_vista": 10.65,
        "preco_30d": "10.80",
        "variacao": "1.75",
        "data_coleta": "2026-01-24"
    },
    {
        "praca": "RS Pelotas (kg)",
        "preco_vista": 10.85,
        "preco_30d": "11.00",
        "variacao": "3.66",
        "data_coleta": "2026-01-24"
    },
    {
        "praca": "BA Sul",
        "preco_vista": 296.5,
        "preco_30d": "300.00",
        "variacao": "-5.89",
        "data_coleta": "2026-01-24"
    },
    {
        "praca": "BA Oeste",
        "preco_vista": 301.5,
        "preco_30d": "305.00",
        "variacao": "-4.30",
        "data_coleta": "2026-01-24"
    },
    {
        "praca": "MT Norte",
        "preco_vista": 295.5,
        "preco_30d": "299.00",
        "variacao": "-6.21",
        "data_coleta": "2026-01-24"
    },
    {
        "praca": "MT Sudoeste",
        "preco_vista": 289.5,
        "preco_30d": "293.00",
        "variacao": "-8.12",
        "data_coleta": "2026-01-24"
    },
    {
        "praca": "MT Cuiabá*",
        "preco_vista": 296.5,
        "preco_30d": "300.00",
        "variacao": "-5.89",
        "data_coleta": "2026-01-24"
    },
    {
        "praca": "MT Sudeste",
        "preco_vista": 296.5,
        "preco_30d": "300.00",
        "variacao": "-5.89",
        "data_coleta": "2026-01-24"
    },
    {
        "praca": "PR Noroeste",
        "preco_vista": 326.0,
        "preco_30d": "330.00",
        "variacao": "3.50",
        "data_coleta": "2026-01-24"
    },
    {
        "praca": "SC",
        "preco_vista": 322.0,
        "preco_30d": "326.00",
        "variacao": "2.23",
        "data_coleta": "2026-01-24"
    },
    {
        "praca": "MA Oeste",
        "preco_vista": 297.5,
        "preco_30d": "301.00",
        "variacao": "-5.57",
        "data_coleta": "2026-01-24"
    },
    {
        "praca": "Alagoas",
        "preco_vista": 306.0,
        "preco_30d": "310.00",
        "variacao": "-2.71",
        "data_coleta": "2026-01-24"
    },
    {
        "praca": "PA Marabá",
        "preco_vista": 299.5,
        "preco_30d": "303.00",
        "variacao": "-4.94",
        "data_coleta": "2026-01-24"
    },
    {
        "praca": "PA Redenção",
        "preco_vista": 293.5,
        "preco_30d": "297.00",
        "variacao": "-6.85",
        "data_coleta": "2026-01-24"
    },
    {
        "praca": "PA Paragominas",
        "preco_vista": 308.0,
        "preco_30d": "312.00",
        "variacao": "-2.07",
        "data_coleta": "2026-01-24"
    },
    {
        "praca": "RO Sudeste",
        "preco_vista": 268.5,
        "preco_30d": "272.00",
        "variacao": "-14.65",
        "data_coleta": "2026-01-24"
    },
    {
        "praca": "TO Sul",
        "preco_vista": 293.5,
        "preco_30d": "297.00",
        "variacao": "-6.85",
        "data_coleta": "2026-01-24"
    },
    {
        "praca": "TO Norte",
        "preco_vista": 296.5,
        "preco_30d": "300.00",
        "variacao": "-5.89",
        "data_coleta": "2026-01-24"
    },
    {
        "praca": "Acre",
        "preco_vista": 260.0,
        "preco_30d": "263.00",
        "variacao": "-17.52",
        "data_coleta": "2026-01-24"
    },
    {
        "praca": "ES",
        "preco_vista": 303.5,
        "preco_30d": "307.00",
        "variacao": "-3.66",
        "data_coleta": "2026-01-24"
    },
    {
        "praca": "RJ",
        "preco_vista": 316.0,
        "preco_30d": "320.00",
        "variacao": "0.32",
        "data_coleta": "2026-01-24"
    },
    {
        "praca": "Roraima",
        "preco_vista": 291.5,
        "preco_30d": "295.00",
        "variacao": "-7.48",
        "data_coleta": "2026-01-24"
    }
]